src/ALU.v
module ALU(
    input [7:0] A, B,
    input [3:0] ALU_Sel,
    output reg [7:0] ALU_Out
);

always @(*) begin
    case(ALU_Sel)
        4'b0000: ALU_Out = A + B;              // ADD
        4'b0001: ALU_Out = A - B;              // SUB
        4'b0010: ALU_Out = A & B;              // AND
        4'b0011: ALU_Out = A | B;              // OR
        4'b0100: ALU_Out = ~(A & B);           // NAND
        4'b0101: ALU_Out = A ^ B;              // XOR
        4'b0110: ALU_Out = ~A;                 // NOT A
        4'b0111: ALU_Out = ~(A | B);           // NOR
        4'b1000: ALU_Out = ~(A ^ B);           // XNOR
        4'b1001: ALU_Out = A + 1;              // Increment A
        4'b1010: ALU_Out = B + A + 1;          // Increment A + B
        4'b1011: ALU_Out = A;                  // Pass A
        4'b1100: ALU_Out = B;                  // Pass B
        4'b1101: ALU_Out = 8'b00000000;        // Reset
        4'b1110: ALU_Out = 8'b11111111;        // Set All 1
        4'b1111: ALU_Out = {A[0], A[1], A[2], A[3], A[4], A[5], A[6], A[7]}; // Reverse A (bit order unchanged here)
        default: ALU_Out = 8'b00000000;
    endcase
end

endmodule

src/testbench.v
module testbench;
    reg [7:0] A, B;
    reg [3:0] ALU_Sel;
    wire [7:0] ALU_Out;

    ALU uut (.A(A), .B(B), .ALU_Sel(ALU_Sel), .ALU_Out(ALU_Out));

    initial begin
        $dumpfile("dump.vcd");
        $dumpvars(0, testbench);

        A = 8'b00001111; B = 8'b00000001;

        // Test all ALU operations
        ALU_Sel = 4'b0000; #10; // ADD
        ALU_Sel = 4'b0001; #10; // SUB
        ALU_Sel = 4'b0010; #10; // AND
        ALU_Sel = 4'b0011; #10; // OR
        ALU_Sel = 4'b0100; #10; // NAND
        ALU_Sel = 4'b0101; #10; // XOR
        ALU_Sel = 4'b0110; #10; // NOT A
        ALU_Sel = 4'b0111; #10; // NOR
        ALU_Sel = 4'b1000; #10; // XNOR
        ALU_Sel = 4'b1001; #10; // Increment A
        ALU_Sel = 4'b1010; #10; // Increment A+B
        ALU_Sel = 4'b1011; #10; // Pass A
        ALU_Sel = 4'b1100; #10; // Pass B
        ALU_Sel = 4'b1101; #10; // Reset
        ALU_Sel = 4'b1110; #10; // Set all 1
        ALU_Sel = 4'b1111; #10; // Reverse A

        $finish;
    end
endmodule

src/dump.vcd
$date
	Wed May 07 00:39:27 2025
$end
$version
	Icarus Verilog
$end
$timescale
	1s
$end
$scope module testbench $end
$var wire 8 ! ALU_Out [7:0] $end
$var reg 8 " A [7:0] $end
$var reg 4 # ALU_Sel [3:0] $end
$var reg 8 $ B [7:0] $end
$scope module uut $end
$var wire 8 % A [7:0] $end
$var wire 4 & ALU_Sel [3:0] $end
$var wire 8 ' B [7:0] $end
$var reg 8 ( ALU_Out [7:0] $end
$upscope $end
$upscope $end
$enddefinitions $end
$comment Show the parameter values. $end
$dumpall
$end
#0
$dumpvars
b10000 (
b1 '
b0 &
b1111 %
b1 $
b0 #
b1111 "
b10000 !
$end
#10
b1110 !
b1110 (
b1 #
b1 &
#20
b1 !
b1 (
b10 #
b10 &
#30
b1111 !
b1111 (
b11 #
b11 &
#40
b11111110 !
b11111110 (
b100 #
b100 &
#50
b1110 !
b1110 (
b101 #
b101 &
#60
b11110000 !
b11110000 (
b110 #
b110 &
#70
b111 #
b111 &
#80
b11110001 !
b11110001 (
b1000 #
b1000 &
#90
b10000 !
b10000 (
b1001 #
b1001 &
#100
b10001 !
b10001 (
b1010 #
b1010 &
#110
b1111 !
b1111 (
b1011 #
b1011 &
#120
b1 !
b1 (
b1100 #
b1100 &
#130
b0 !
b0 (
b1101 #
b1101 &
#140
b11111111 !
b11111111 (
b1110 #
b1110 &
#150
b11110000 !
b11110000 (
b1111 #
b1111 &
